{"cameraMode":{"drawMode":0,"name":"Shaded","section":"Shading Mode"},"sceneLighting":false,"audioPlay":false,"sceneViewState":{"m_AlwaysRefresh":false,"showFog":true,"showSkybox":false,"showFlares":true,"showImageEffects":true,"showParticleSystems":true,"showVisualEffectGraphs":true,"m_FxEnabled":true},"in2DMode":false,"pivot":{"x":9.192815780639649,"y":0.5619689226150513,"z":4.60245943069458},"rotation":{"x":-0.10580911487340927,"y":-0.859787106513977,"z":0.1984221190214157,"w":-0.4584816098213196},"size":0.36199837923049929,"orthographic":false}